authkeyman/__init__.py
authkeyman/authkeyman.py
authkeyman/authorized_key.py
authkeyman/authorized_keys_file.py
authkeyman-1.1.1.dist-info/LICENSE
authkeyman-1.1.1.dist-info/METADATA
authkeyman-1.1.1.dist-info/WHEEL
authkeyman-1.1.1.dist-info/entry_points.txt
authkeyman-1.1.1.dist-info/RECORD
