Metadata-Version: 2.3
Name: authkeyman
Version: 1.1.1
Summary: Quickly manage your authorized public SSH keys
License: GPL-3.0-only
Keywords: authorized_keys,ssh,cli,command-line,command,line,tool
Author: Tactical Laptop Bag
Author-email: tacticallaptopbag@protonmail.com
Requires-Python: >=3.9
Classifier: Development Status :: 5 - Production/Stable
Classifier: Intended Audience :: System Administrators
Classifier: Environment :: Console
Classifier: Operating System :: OS Independent
Requires-Dist: argparse (>=1.0.0,<2.0.0)
Requires-Dist: pathlib (>=1.0.0,<2.0.0)
Project-URL: Issues, https://github.com/TacticalLaptopBag/authkeyman/issues
Project-URL: Repository, https://github.com/TacticalLaptopBag/authkeyman
